my_robot/__init__.py
my_robot/my_robot_env.py
my_robot/test.py
my_robot/envs/__init__.py
my_robot/envs/my_robot_env.py
my_robot-1.0.4.dist-info/METADATA
my_robot-1.0.4.dist-info/WHEEL
my_robot-1.0.4.dist-info/top_level.txt
my_robot-1.0.4.dist-info/RECORD
