Metadata-Version: 2.1
Name: my-robot
Version: 1.0.4
Summary: None
Home-page: UNKNOWN
Author: Ahao
Author-email: 
License: UNKNOWN
Keywords: python,flink,arg,toml,windows,linux
Platform: UNKNOWN
Classifier: Development Status :: 1 - Planning
Classifier: Intended Audience :: Developers
Classifier: Programming Language :: Python :: 3
Classifier: Operating System :: Microsoft :: Windows
Classifier: Operating System :: Unix
Requires-Dist: gym
Requires-Dist: getch; platform_system == "linux"
Requires-Dist: getch; platform_system == "windows"
